source_pardot/__init__.py
source_pardot/api.py
source_pardot/run.py
source_pardot/schemas/campaigns.json
source_pardot/schemas/email_clicks.json
source_pardot/schemas/list_membership.json
source_pardot/schemas/lists.json
source_pardot/schemas/opportunities.json
source_pardot/schemas/prospect_accounts.json
source_pardot/schemas/prospects.json
source_pardot/schemas/users.json
source_pardot/schemas/visitor_activities.json
source_pardot/schemas/visitors.json
source_pardot/schemas/visits.json
source_pardot/source.py
source_pardot/spec.json
source_pardot/stream.py
airbyte_source_pardot-0.1.22.dist-info/METADATA
airbyte_source_pardot-0.1.22.dist-info/WHEEL
airbyte_source_pardot-0.1.22.dist-info/entry_points.txt
airbyte_source_pardot-0.1.22.dist-info/RECORD
